cpvexcel/__init__.py
cpvexcel/__main__.py
cpvexcel/dw_zip.py
cpvexcel/pr_path.py
cpvexcel/pr_url.py
cpvexcel/tree_view.py
cpvexcel/utils.py
cpvx-1.0.1.dist-info/licenses/LICENSE.md
cpvx-1.0.1.dist-info/METADATA
cpvx-1.0.1.dist-info/WHEEL
cpvx-1.0.1.dist-info/entry_points.txt
cpvx-1.0.1.dist-info/top_level.txt
cpvx-1.0.1.dist-info/RECORD
